setup.py
stacklogger.py
stacklogger.egg-info/PKG-INFO
stacklogger.egg-info/SOURCES.txt
stacklogger.egg-info/dependency_links.txt
stacklogger.egg-info/requires.txt
stacklogger.egg-info/top_level.txt