Metadata-Version: 1.0
Name: stacklogger
Version: 0.1.0
Summary: A stack-aware logging extension
Home-page: http://packages.python.org/stacklogger
Author: Will Maier
Author-email: willmaier@ml1.net
License: UNKNOWN
Keywords: logging stack frame
Platform: UNKNOWN
Classifier: Development Status :: 3 - Alpha
Classifier: Intended Audience :: Developers
Classifier: License :: OSI Approved :: BSD License
Classifier: License :: OSI Approved :: MIT License
Classifier: Natural Language :: English
Classifier: Programming Language :: Python
Classifier: Topic :: System :: Logging
